robinson
setup.py
librobinson.egg-info/PKG-INFO
librobinson.egg-info/SOURCES.txt
librobinson.egg-info/dependency_links.txt
librobinson.egg-info/top_level.txt
robinson/__init__.py
robinson/book.py
robinson/booknames.py
robinson/chapter.py
robinson/convert.py
robinson/kind.py
robinson/reader.py
robinson/readwhat.py
robinson/robinson.py
robinson/robinsontags.py
robinson/variant.py
robinson/verse.py
robinson/word.py