Metadata-Version: 1.0
Name: librobinson
Version: 0.2.1
Summary: A library to parse and convert the New Testament Greek files of Dr. Maurice A. Robinson
Home-page: http://github.com/byztxt/librobinson
Author: Ulrik Sandborg-Petersen
Author-email: ulrikp@scripturesys.com
License: MIT
Keywords: Maurice A. Robinson,New Testament Greek,parse,convert
Platform: UNKNOWN
